winval/__init__.py
winval/antlr/winval.interp
winval/antlr/winval.tokens
winval/antlr/winvalLexer.interp
winval/antlr/winvalLexer.py
winval/antlr/winvalLexer.tokens
winval/antlr/winvalListener.py
winval/antlr/winvalParser.py
winval/antlr/winvalVisitor.py
winval/cloud_files_validator.py
winval/constraint_eval.py
winval/constraints_pre_processor.py
winval/parsed_workflow_inputs.py
winval/python_extensions.py
winval/validate_wdl_constraints.py
winval/wdl_parser.py
winval/winval.g4
winval/winval_class.py
winval/workflow_var.py
winval-0.8.0.dist-info/LICENSE
winval-0.8.0.dist-info/METADATA
winval-0.8.0.dist-info/WHEEL
winval-0.8.0.dist-info/RECORD
