Metadata-Version: 2.1
Name: winval
Version: 0.8.0
Summary: WDL workflow inputs validation
License: Apache-2.0
Author: doron
Author-email: doron.shemtov@ultimagen.com
Requires-Python: >=3.8,<4.0
Classifier: License :: OSI Approved :: Apache Software License
Classifier: Programming Language :: Python :: 3
Classifier: Programming Language :: Python :: 3.8
Classifier: Programming Language :: Python :: 3.9
Classifier: Programming Language :: Python :: 3.10
Classifier: Programming Language :: Python :: 3.11
Classifier: Programming Language :: Python :: 3.12
Requires-Dist: antlr4-python3-runtime (==4.10)
Requires-Dist: boto3 (>=1.29,<2.0)
Requires-Dist: google-cloud-storage (>=2.5.0,<3.0.0)
